py_mess_server_by_rufus-0.0.1.data/scripts/server_run
server/__init__.py
server/server.py
server/common/__init__.py
server/common/decos.py
server/common/descryptors.py
server/common/errors.py
server/common/metaclasses.py
server/common/utils.py
server/common/variables.py
server/logs/__init__.py
server/logs/config_client_log.py
server/logs/config_server_log.py
server/server_side/__init__.py
server/server_side/add_user.py
server/server_side/config_window.py
server/server_side/core.py
server/server_side/database.py
server/server_side/main_window.py
server/server_side/remove_user.py
server/server_side/stat_window.py
server/unit_tests/__init__.py
server/unit_tests/test_client.py
server/unit_tests/test_utils.py
py_mess_server_by_rufus-0.0.1.dist-info/METADATA
py_mess_server_by_rufus-0.0.1.dist-info/WHEEL
py_mess_server_by_rufus-0.0.1.dist-info/top_level.txt
py_mess_server_by_rufus-0.0.1.dist-info/RECORD
